omnisci/__init__.py
omnisci/common/__init__.py
omnisci/common/constants.py
omnisci/common/ttypes.py
omnisci/completion_hints/__init__.py
omnisci/completion_hints/constants.py
omnisci/completion_hints/ttypes.py
omnisci/extension_functions/__init__.py
omnisci/extension_functions/constants.py
omnisci/extension_functions/ttypes.py
omnisci/serialized_result_set/__init__.py
omnisci/serialized_result_set/constants.py
omnisci/serialized_result_set/ttypes.py
omnisci/thrift/OmniSci.py
omnisci/thrift/__init__.py
omnisci/thrift/constants.py
omnisci/thrift/ttypes.py
pymapd/__init__.py
pymapd/_loaders.py
pymapd/_mutators.py
pymapd/_pandas_loaders.py
pymapd/_parsers.py
pymapd/_samlutils.py
pymapd/_transforms.py
pymapd/_utils.py
pymapd/connection.py
pymapd/cursor.py
pymapd/dtypes.py
pymapd/exceptions.py
pymapd/ipc.py
tests/__init__.py
tests/conftest.py
tests/test_connection.py
tests/test_cursor.py
tests/test_data_no_nulls_cpu.py
tests/test_data_no_nulls_gpu.py
tests/test_deallocate.py
tests/test_integration.py
tests/test_loaders.py
tests/test_results_set.py
tests/test_runtime_udf.py
pymapd-0.24.1.dist-info/LICENSE.md
pymapd-0.24.1.dist-info/METADATA
pymapd-0.24.1.dist-info/WHEEL
pymapd-0.24.1.dist-info/top_level.txt
pymapd-0.24.1.dist-info/RECORD
